[
    {
        "name": "Kingston Fury Beast Black 32GB (2x16GB)",
        "specs": "DDR5 / CL30 / 32 GB / 6000 MHz / DDR5 SDRAM",
        "price": "1 389 kr"
    },
    {
        "name": "Kingston Fury Beast Black 64GB (2x32B)",
        "specs": "DDR5 / CL30 / 64 GB / 6000 MHz / DDR5 SDRAM",
        "price": "2 749 kr"
    },
    {
        "name": "Kingston Fury Beast 32GB (2x16GB)",
        "specs": "DDR4 / CL16 / 32 GB / 3200 MHz / DDR4 SDRAM",
        "price": "777 kr"
    },
    {
        "name": "G.Skill Flare X5 32GB (2x16GB)",
        "specs": "DDR5 / CL30 / 32 GB / 6000 MHz / DDR5 SDRAM",
        "price": "1 349 kr"
    },
    {
        "name": "Corsair Vengeance LPX Black 64GB (2x32GB)",
        "specs": "DDR4 / CL18 / 64 GB / 3600 MHz / DDR4 SDRAM",
        "price": "1 589 kr"
    },
    {
        "name": "Kingston Fury Beast Black 32GB (2x16GB)",
        "specs": "DDR5 / CL32 / 32 GB / 6400 MHz / DDR5 SDRAM",
        "price": "1 639 kr"
    },
    {
        "name": "Corsair Vengeance 64GB (2x32GB)",
        "specs": "DDR5 / CL30 / 64 GB / 6000 MHz / DDR5 SDRAM",
        "price": "3 059 kr"
    },
    {
        "name": "Corsair Vengeance 96GB (2x48GB)",
        "specs": "DDR5 / CL30 / 96 GB / 3000 MHz / DDR5 SDRAM",
        "price": "4 539 kr"
    },
    {
        "name": "Corsair Vengeance RGB 32GB (2x16GB)",
        "specs": "DDR5 / CL36 / 32 GB / 5600 MHz / DDR5 SDRAM",
        "price": "1 290 kr\n1 549 kr"
    },
    {
        "name": "G.Skill Trident Z5 Neo RGB 32GB (2x16GB)",
        "specs": "DDR5 / CL30 / 32 GB / 6000 MHz / DDR5 SDRAM",
        "price": "1 590 kr"
    },
    {
        "name": "Kingston Fury Impact 64GB (2x32GB)",
        "specs": "SODIMM DDR4 / CL20 / 64 GB / 3200 MHz / DDR4 SDRAM",
        "price": "1 549 kr"
    },
    {
        "name": "Kingston Fury Impact 64GB (2x32GB) / 5600Mhz / CL40",
        "specs": "SODIMM DDR5 / CL40 / 64 GB / 5600 MHz / DDR5 SDRAM",
        "price": "2 390 kr"
    },
    {
        "name": "Corsair Vengeance LPX Black 32GB (2x16GB) Ryzen",
        "specs": "DDR4 / CL18 / 32 GB / 3600 MHz / DDR4 SDRAM",
        "price": "866 kr"
    },
    {
        "name": "Kingston Fury Beast 16GB (2x8GB)",
        "specs": "DDR4 / CL16 / 16 GB / 3200 MHz / DDR4 SDRAM",
        "price": "444 kr"
    },
    {
        "name": "Kingston Fury Impact 64GB (2x32GB) / 4800Mhz / CL38",
        "specs": "SODIMM DDR5 / CL38 / 64 GB / 4800 MHz / DDR5 SDRAM",
        "price": "2 249 kr"
    },
    {
        "name": "Corsair Vengeance 32GB (2x16GB)",
        "specs": "DDR5 / CL32 / 32 GB / 6400 MHz / DDR5 SDRAM",
        "price": "1 649 kr"
    },
    {
        "name": "Kingston Fury Beast 32GB (2x16GB)",
        "specs": "DDR4 / CL18 / 32 GB / 3600 MHz / DDR4 SDRAM",
        "price": "899 kr"
    },
    {
        "name": "Corsair Vengeance 32GB (2x16GB)",
        "specs": "DDR5 / CL40 / 32 GB / 5200 MHz / DDR5 SDRAM",
        "price": "1 149 kr"
    },
    {
        "name": "G.SKill Trident Z Neo RGB 16GB (2x8GB)",
        "specs": "DDR4 / CL16 / 16 GB / 3600 MHz / DDR4 SDRAM",
        "price": "869 kr"
    },
    {
        "name": "Kingston Fury Beast 64GB (2x32GB)",
        "specs": "DDR4 / CL16 / 64 GB / 3200 MHz / DDR4 SDRAM",
        "price": "1 395 kr"
    },
    {
        "name": "Corsair Vengeance RGB PRO 32GB (2x16GB)",
        "specs": "DDR4 / CL16 / 32 GB / 3200 MHz / DDR4 SDRAM",
        "price": "1 066 kr"
    },
    {
        "name": "Kingston Fury Impact 32GB (2x16GB) / 5600Mhz / CL40",
        "specs": "SODIMM DDR5 / CL40 / 32 GB / 5600 MHz / DDR5 SDRAM",
        "price": "1 289 kr"
    },
    {
        "name": "Kingston Fury Beast RGB 64GB (2x32GB)",
        "specs": "DDR5 / CL30 / 64 GB / 6000 MHz / DDR5 SDRAM",
        "price": "2 789 kr"
    },
    {
        "name": "Corsair Vengeance 16GB (1x16GB)",
        "specs": "SODIMM DDR4 / CL16 / 16 GB / 2400 MHz / DDR4 SDRAM",
        "price": "415 kr"
    },
    {
        "name": "Kingston Fury Beast Black 32GB (2x16GB)",
        "specs": "DDR5 / CL30 / 32 GB / 6000 MHz / DDR5 SDRAM",
        "price": "1 389 kr"
    },
    {
        "name": "Kingston Fury Beast Black 64GB (2x32B)",
        "specs": "DDR5 / CL30 / 64 GB / 6000 MHz / DDR5 SDRAM",
        "price": "2 749 kr"
    },
    {
        "name": "Kingston Fury Beast 32GB (2x16GB)",
        "specs": "DDR4 / CL16 / 32 GB / 3200 MHz / DDR4 SDRAM",
        "price": "777 kr"
    },
    {
        "name": "G.Skill Flare X5 32GB (2x16GB)",
        "specs": "DDR5 / CL30 / 32 GB / 6000 MHz / DDR5 SDRAM",
        "price": "1 349 kr"
    },
    {
        "name": "Corsair Vengeance LPX Black 64GB (2x32GB)",
        "specs": "DDR4 / CL18 / 64 GB / 3600 MHz / DDR4 SDRAM",
        "price": "1 589 kr"
    },
    {
        "name": "Kingston Fury Beast Black 32GB (2x16GB)",
        "specs": "DDR5 / CL32 / 32 GB / 6400 MHz / DDR5 SDRAM",
        "price": "1 639 kr"
    },
    {
        "name": "Corsair Vengeance 64GB (2x32GB)",
        "specs": "DDR5 / CL30 / 64 GB / 6000 MHz / DDR5 SDRAM",
        "price": "3 059 kr"
    },
    {
        "name": "Corsair Vengeance 96GB (2x48GB)",
        "specs": "DDR5 / CL30 / 96 GB / 3000 MHz / DDR5 SDRAM",
        "price": "4 539 kr"
    },
    {
        "name": "Corsair Vengeance RGB 32GB (2x16GB)",
        "specs": "DDR5 / CL36 / 32 GB / 5600 MHz / DDR5 SDRAM",
        "price": "1 290 kr\n1 549 kr"
    },
    {
        "name": "G.Skill Trident Z5 Neo RGB 32GB (2x16GB)",
        "specs": "DDR5 / CL30 / 32 GB / 6000 MHz / DDR5 SDRAM",
        "price": "1 590 kr"
    },
    {
        "name": "Kingston Fury Impact 64GB (2x32GB)",
        "specs": "SODIMM DDR4 / CL20 / 64 GB / 3200 MHz / DDR4 SDRAM",
        "price": "1 549 kr"
    },
    {
        "name": "Kingston Fury Impact 64GB (2x32GB) / 5600Mhz / CL40",
        "specs": "SODIMM DDR5 / CL40 / 64 GB / 5600 MHz / DDR5 SDRAM",
        "price": "2 390 kr"
    },
    {
        "name": "Corsair Vengeance LPX Black 32GB (2x16GB) Ryzen",
        "specs": "DDR4 / CL18 / 32 GB / 3600 MHz / DDR4 SDRAM",
        "price": "866 kr"
    },
    {
        "name": "Kingston Fury Beast 16GB (2x8GB)",
        "specs": "DDR4 / CL16 / 16 GB / 3200 MHz / DDR4 SDRAM",
        "price": "444 kr"
    },
    {
        "name": "Kingston Fury Impact 64GB (2x32GB) / 4800Mhz / CL38",
        "specs": "SODIMM DDR5 / CL38 / 64 GB / 4800 MHz / DDR5 SDRAM",
        "price": "2 249 kr"
    },
    {
        "name": "Corsair Vengeance 32GB (2x16GB)",
        "specs": "DDR5 / CL32 / 32 GB / 6400 MHz / DDR5 SDRAM",
        "price": "1 649 kr"
    },
    {
        "name": "Kingston Fury Beast 32GB (2x16GB)",
        "specs": "DDR4 / CL18 / 32 GB / 3600 MHz / DDR4 SDRAM",
        "price": "899 kr"
    },
    {
        "name": "Corsair Vengeance 32GB (2x16GB)",
        "specs": "DDR5 / CL40 / 32 GB / 5200 MHz / DDR5 SDRAM",
        "price": "1 149 kr"
    },
    {
        "name": "G.SKill Trident Z Neo RGB 16GB (2x8GB)",
        "specs": "DDR4 / CL16 / 16 GB / 3600 MHz / DDR4 SDRAM",
        "price": "869 kr"
    },
    {
        "name": "Kingston Fury Beast 64GB (2x32GB)",
        "specs": "DDR4 / CL16 / 64 GB / 3200 MHz / DDR4 SDRAM",
        "price": "1 395 kr"
    },
    {
        "name": "Corsair Vengeance RGB PRO 32GB (2x16GB)",
        "specs": "DDR4 / CL16 / 32 GB / 3200 MHz / DDR4 SDRAM",
        "price": "1 066 kr"
    },
    {
        "name": "Kingston Fury Impact 32GB (2x16GB) / 5600Mhz / CL40",
        "specs": "SODIMM DDR5 / CL40 / 32 GB / 5600 MHz / DDR5 SDRAM",
        "price": "1 289 kr"
    },
    {
        "name": "Kingston Fury Beast RGB 64GB (2x32GB)",
        "specs": "DDR5 / CL30 / 64 GB / 6000 MHz / DDR5 SDRAM",
        "price": "2 789 kr"
    },
    {
        "name": "Corsair Vengeance 16GB (1x16GB)",
        "specs": "SODIMM DDR4 / CL16 / 16 GB / 2400 MHz / DDR4 SDRAM",
        "price": "415 kr"
    },
    {
        "name": "Kingston Fury Beast Black 16GB (2x8GB)",
        "specs": "DDR5 / CL30 / 16 GB / 6000 MHz / DDR5 SDRAM",
        "price": "839 kr"
    },
    {
        "name": "Kingston Fury Beast RGB 16GB (2x8GB)",
        "specs": "DDR4 / CL16 / 16 GB / 3200 MHz / DDR4 SDRAM",
        "price": "659 kr"
    },
    {
        "name": "Kingston Fury Beast RGB 32GB (2x16GB)",
        "specs": "DDR4 / CL16 / 32 GB / 3200 MHz / DDR4 SDRAM",
        "price": "990 kr"
    },
    {
        "name": "Corsair Vengeance 16GB (2x8GB)",
        "specs": "DDR3 / CL10 / 16 GB / 1600 MHz / DDR3 SDRAM",
        "price": "1 049 kr"
    },
    {
        "name": "Kingston Fury Beast RGB 32GB (2x16GB)",
        "specs": "DDR5 / CL36 / 32 GB / 5600 MHz / DDR5 SDRAM",
        "price": "1 449 kr"
    },
    {
        "name": "Corsair Vengeance LPX Black 64GB (2x32GB)",
        "specs": "DDR4 / CL16 / 64 GB / 3200 MHz / DDR4 SDRAM",
        "price": "1 569 kr"
    },
    {
        "name": "Corsair Mac Memory 8GB (2x4GB)",
        "specs": "SODIMM DDR3 / CL9 / 8 GB / 1333 MHz / DDR3 SDRAM",
        "price": "539 kr"
    },
    {
        "name": "Corsair Vengeance 32GB (2x16GB)",
        "specs": "DDR5 / CL30 / 32 GB / 6000 MHz / DDR5 SDRAM",
        "price": "1 490 kr"
    },
    {
        "name": "Corsair Vengeance RGB PRO 32GB (2x16GB) Ryzen",
        "specs": "DDR4 / CL18 / 32 GB / 3600 MHz / DDR4 SDRAM",
        "price": "999 kr"
    },
    {
        "name": "Kingston Fury Beast RGB 32GB (2x16GB)",
        "specs": "DDR5 / CL30 / 32 GB / 6000 MHz / DDR5 SDRAM",
        "price": "1 590 kr"
    },
    {
        "name": "Corsair Vengeance LPX Black 16GB (2x8GB)",
        "specs": "DDR4 / CL16 / 16 GB / 2666 MHz / DDR4 SDRAM",
        "price": "519 kr"
    },
    {
        "name": "Corsair Vengeance 32GB (2x16GB)",
        "specs": "DDR5 / CL36 / 32 GB / 6000 MHz / DDR5 SDRAM",
        "price": "1 290 kr"
    },
    {
        "name": "Corsair Vengeance LPX Black 32GB (2x16GB)",
        "specs": "DDR4 / CL16 / 32 GB / 3200 MHz / DDR4 SDRAM",
        "price": "819 kr"
    },
    {
        "name": "Corsair Dominator Titanium Accessory Kit - Black",
        "specs": "DDR5",
        "price": "349 kr"
    },
    {
        "name": "Kingston Fury Impact 16GB (1x16GB) / 4800Mhz / CL38",
        "specs": "SODIMM DDR5 / CL38 / 16 GB / 4800 MHz / DDR5 SDRAM",
        "price": "639 kr"
    },
    {
        "name": "Corsair Vengeance RGB 32GB (2x16GB)",
        "specs": "DDR5 / CL36 / 32 GB / 6000 MHz / DDR5 SDRAM",
        "price": "1 490 kr"
    },
    {
        "name": "Kingston Fury Beast 32GB (2x16GB)",
        "specs": "DDR4 / CL16 / 32 GB / 3200 MHz / DDR4 SDRAM",
        "price": "829 kr"
    },
    {
        "name": "Corsair Vengeance LPX Black 16GB (2x8GB)",
        "specs": "DDR4 / CL16 / 16 GB / 3200 MHz / DDR4 SDRAM",
        "price": "499 kr"
    },
    {
        "name": "Kingston Fury Beast Black 32GB (2x16GB)",
        "specs": "DDR5 / CL30 / 32 GB / 6000 MHz / DDR5 SDRAM",
        "price": "1 469 kr"
    },
    {
        "name": "Kingston Fury Impact 16GB (1x16GB)",
        "specs": "SODIMM DDR4 / CL20 / 16 GB / 3200 MHz / DDR4 SDRAM",
        "price": "419 kr"
    },
    {
        "name": "Corsair Vengeance RGB 32GB (2x16GB)",
        "specs": "DDR5 / CL36 / 32 GB / 6200 MHz / DDR5 SDRAM",
        "price": "1 739 kr"
    },
    {
        "name": "Kingston Fury Beast RGB 32GB (2x16GB)",
        "specs": "DDR5 / CL30 / 32 GB / 6000 MHz / DDR5 SDRAM",
        "price": "1 590 kr"
    },
    {
        "name": "Corsair Vengeance 16GB (2x8GB)",
        "specs": "SODIMM DDR4 / CL18 / 16 GB / 2666 MHz / DDR4 SDRAM",
        "price": "519 kr"
    },
    {
        "name": "Kingston Fury Impact 8GB (1x8GB)",
        "specs": "SODIMM DDR4 / CL20 / 8 GB / 3200 MHz / DDR4 SDRAM",
        "price": "255 kr"
    },
    {
        "name": "Kingston Fury Beast Black 16GB (2x8GB)",
        "specs": "DDR5 / CL30 / 16 GB / 6000 MHz / DDR5 SDRAM",
        "price": "839 kr"
    },
    {
        "name": "Kingston Fury Beast RGB 16GB (2x8GB)",
        "specs": "DDR4 / CL16 / 16 GB / 3200 MHz / DDR4 SDRAM",
        "price": "659 kr"
    },
    {
        "name": "Kingston Fury Beast RGB 32GB (2x16GB)",
        "specs": "DDR4 / CL16 / 32 GB / 3200 MHz / DDR4 SDRAM",
        "price": "990 kr"
    },
    {
        "name": "Corsair Vengeance 16GB (2x8GB)",
        "specs": "DDR3 / CL10 / 16 GB / 1600 MHz / DDR3 SDRAM",
        "price": "1 049 kr"
    },
    {
        "name": "Kingston Fury Beast RGB 32GB (2x16GB)",
        "specs": "DDR5 / CL36 / 32 GB / 5600 MHz / DDR5 SDRAM",
        "price": "1 449 kr"
    },
    {
        "name": "Corsair Vengeance LPX Black 64GB (2x32GB)",
        "specs": "DDR4 / CL16 / 64 GB / 3200 MHz / DDR4 SDRAM",
        "price": "1 569 kr"
    },
    {
        "name": "Corsair Mac Memory 8GB (2x4GB)",
        "specs": "SODIMM DDR3 / CL9 / 8 GB / 1333 MHz / DDR3 SDRAM",
        "price": "539 kr"
    },
    {
        "name": "Corsair Vengeance 32GB (2x16GB)",
        "specs": "DDR5 / CL30 / 32 GB / 6000 MHz / DDR5 SDRAM",
        "price": "1 490 kr"
    },
    {
        "name": "Corsair Vengeance RGB PRO 32GB (2x16GB) Ryzen",
        "specs": "DDR4 / CL18 / 32 GB / 3600 MHz / DDR4 SDRAM",
        "price": "999 kr"
    },
    {
        "name": "Kingston Fury Beast RGB 32GB (2x16GB)",
        "specs": "DDR5 / CL30 / 32 GB / 6000 MHz / DDR5 SDRAM",
        "price": "1 590 kr"
    },
    {
        "name": "Corsair Vengeance LPX Black 16GB (2x8GB)",
        "specs": "DDR4 / CL16 / 16 GB / 2666 MHz / DDR4 SDRAM",
        "price": "519 kr"
    },
    {
        "name": "Corsair Vengeance 32GB (2x16GB)",
        "specs": "DDR5 / CL36 / 32 GB / 6000 MHz / DDR5 SDRAM",
        "price": "1 290 kr"
    },
    {
        "name": "Corsair Vengeance LPX Black 32GB (2x16GB)",
        "specs": "DDR4 / CL16 / 32 GB / 3200 MHz / DDR4 SDRAM",
        "price": "819 kr"
    },
    {
        "name": "Corsair Dominator Titanium Accessory Kit - Black",
        "specs": "DDR5",
        "price": "349 kr"
    },
    {
        "name": "Kingston Fury Impact 16GB (1x16GB) / 4800Mhz / CL38",
        "specs": "SODIMM DDR5 / CL38 / 16 GB / 4800 MHz / DDR5 SDRAM",
        "price": "639 kr"
    },
    {
        "name": "Corsair Vengeance RGB 32GB (2x16GB)",
        "specs": "DDR5 / CL36 / 32 GB / 6000 MHz / DDR5 SDRAM",
        "price": "1 490 kr"
    },
    {
        "name": "Kingston Fury Beast 32GB (2x16GB)",
        "specs": "DDR4 / CL16 / 32 GB / 3200 MHz / DDR4 SDRAM",
        "price": "829 kr"
    },
    {
        "name": "Corsair Vengeance LPX Black 16GB (2x8GB)",
        "specs": "DDR4 / CL16 / 16 GB / 3200 MHz / DDR4 SDRAM",
        "price": "499 kr"
    },
    {
        "name": "Kingston Fury Beast Black 32GB (2x16GB)",
        "specs": "DDR5 / CL30 / 32 GB / 6000 MHz / DDR5 SDRAM",
        "price": "1 469 kr"
    },
    {
        "name": "Kingston Fury Impact 16GB (1x16GB)",
        "specs": "SODIMM DDR4 / CL20 / 16 GB / 3200 MHz / DDR4 SDRAM",
        "price": "419 kr"
    },
    {
        "name": "Corsair Vengeance RGB 32GB (2x16GB)",
        "specs": "DDR5 / CL36 / 32 GB / 6200 MHz / DDR5 SDRAM",
        "price": "1 739 kr"
    },
    {
        "name": "Kingston Fury Beast RGB 32GB (2x16GB)",
        "specs": "DDR5 / CL30 / 32 GB / 6000 MHz / DDR5 SDRAM",
        "price": "1 590 kr"
    },
    {
        "name": "Corsair Vengeance 16GB (2x8GB)",
        "specs": "SODIMM DDR4 / CL18 / 16 GB / 2666 MHz / DDR4 SDRAM",
        "price": "519 kr"
    },
    {
        "name": "Kingston Fury Impact 8GB (1x8GB)",
        "specs": "SODIMM DDR4 / CL20 / 8 GB / 3200 MHz / DDR4 SDRAM",
        "price": "255 kr"
    },
    {
        "name": "Corsair Vengeance LPX Black 8GB (1x8GB)",
        "specs": "DDR4 / CL16 / 8 GB / 2666 MHz / DDR4 SDRAM",
        "price": "259 kr"
    },
    {
        "name": "Kingston Fury Beast Black 32GB (2x16GB)",
        "specs": "DDR5 / CL30 / 32 GB / 6000 MHz / DDR5 SDRAM",
        "price": "1 589 kr"
    },
    {
        "name": "Corsair Vengeance 32GB (2x16GB)",
        "specs": "DDR5 / CL36 / 32 GB / 6000 MHz / DDR5 SDRAM",
        "price": "1 389 kr"
    },
    {
        "name": "Corsair Vengeance 64GB (2x32GB)",
        "specs": "DDR5 / CL32 / 64 GB / 6600 MHz / DDR5 SDRAM",
        "price": "3 134 kr"
    },
    {
        "name": "Corsair Vengeance RGB 32GB (2x16GB)",
        "specs": "DDR5 / CL36 / 32 GB / 6000 MHz / DDR5 SDRAM",
        "price": "1 439 kr"
    },
    {
        "name": "Corsair Vengeance RGB 32GB (2x16GB)",
        "specs": "DDR5 / CL30 / 32 GB / 6000 MHz / DDR5 SDRAM",
        "price": "1 790 kr"
    },
    {
        "name": "Corsair Vengeance RGB PRO 16GB (2x8GB)",
        "specs": "DDR4 / CL16 / 16 GB / 3200 MHz / DDR4 SDRAM",
        "price": "689 kr"
    },
    {
        "name": "Kingston Fury Beast 16GB (1x16GB)",
        "specs": "DDR4 / CL16 / 16 GB / 3200 MHz / DDR4 SDRAM",
        "price": "429 kr"
    },
    {
        "name": "Kingston Fury Beast RGB 32GB (2x16GB)",
        "specs": "DDR5 / CL30 / 32 GB / 6000 MHz / DDR5 SDRAM",
        "price": "1 589 kr"
    },
    {
        "name": "Corsair Vengeance 32GB (2x16GB)",
        "specs": "DDR5 / CL30 / 32 GB / 6000 MHz / DDR5 SDRAM",
        "price": "1 590 kr"
    },
    {
        "name": "Corsair Vengeance 8GB (1x8GB)",
        "specs": "SODIMM DDR4 / CL16 / 8 GB / 2400 MHz / DDR4 SDRAM",
        "price": "269 kr"
    },
    {
        "name": "Corsair Vengeance RGB PRO 16GB (2x8GB)",
        "specs": "DDR4 / CL18 / 16 GB / 3600 MHz / DDR4 SDRAM",
        "price": "689 kr"
    },
    {
        "name": "Corsair Vengeance Low Profile 8GB (2x4GB) 1600MHz",
        "specs": "DDR3 / CL9 / 8 GB / 1600 MHz / DDR3 SDRAM",
        "price": "639 kr"
    },
    {
        "name": "Kingston Fury Beast Black 64GB (2x32B)",
        "specs": "DDR5 / CL30 / 64 GB / 6000 MHz / DDR5 SDRAM",
        "price": "2 729 kr"
    },
    {
        "name": "Corsair Vengeance RGB 32GB (2x16GB)",
        "specs": "DDR5 / CL40 / 32 GB / 5200 MHz / DDR5 SDRAM",
        "price": "1 379 kr"
    },
    {
        "name": "Kingston Fury Impact 32GB (2x16GB)",
        "specs": "SODIMM DDR4 / CL20 / 32 GB / 3200 MHz / DDR4 SDRAM",
        "price": "899 kr"
    },
    {
        "name": "Kingston Fury Beast Black 32GB (2x16GB)",
        "specs": "DDR5 / CL36 / 32 GB / 5200 MHz / DDR5 SDRAM",
        "price": "1 189 kr"
    },
    {
        "name": "Kingston Fury Beast RGB 64GB (2x32GB)",
        "specs": "DDR5 / CL30 / 64 GB / 6000 MHz / DDR5 SDRAM",
        "price": "2 848 kr"
    },
    {
        "name": "Corsair Vengeance 32GB (2x16GB)",
        "specs": "DDR5 / CL40 / 32 GB / 5200 MHz / DDR5 SDRAM",
        "price": "1 199 kr"
    },
    {
        "name": "Kingston Fury Beast RGB 64GB (2x32GB)",
        "specs": "DDR5 / CL36 / 64 GB / 6000 MHz / DDR5 SDRAM",
        "price": "2 790 kr"
    },
    {
        "name": "G.SKill Trident Z Neo RGB 32GB (2x16GB)",
        "specs": "DDR4 / CL16 / 32 GB / 3600 MHz / DDR4 SDRAM",
        "price": "1 399 kr"
    },
    {
        "name": "G.Skill Trident Z5 Neo 32GB (2x16GB)",
        "specs": "DDR5 / CL30 / 32 GB / 6000 MHz / DDR5 SDRAM",
        "price": "1 569 kr"
    },
    {
        "name": "Corsair Vengeance LPX Black 16GB (2x8GB)",
        "specs": "DDR4 / CL16 / 16 GB / 3200 MHz / DDR4 SDRAM",
        "price": "519 kr"
    },
    {
        "name": "Corsair Vengeance LPX Black 16GB (2x8GB) Ryzen",
        "specs": "DDR4 / CL18 / 16 GB / 3600 MHz / DDR4 SDRAM",
        "price": "518 kr"
    },
    {
        "name": "Corsair Vengeance LPX Black 8GB (1x8GB)",
        "specs": "DDR4 / CL16 / 8 GB / 2666 MHz / DDR4 SDRAM",
        "price": "259 kr"
    },
    {
        "name": "Kingston Fury Beast Black 32GB (2x16GB)",
        "specs": "DDR5 / CL30 / 32 GB / 6000 MHz / DDR5 SDRAM",
        "price": "1 589 kr"
    },
    {
        "name": "Corsair Vengeance 32GB (2x16GB)",
        "specs": "DDR5 / CL36 / 32 GB / 6000 MHz / DDR5 SDRAM",
        "price": "1 389 kr"
    },
    {
        "name": "Corsair Vengeance 64GB (2x32GB)",
        "specs": "DDR5 / CL32 / 64 GB / 6600 MHz / DDR5 SDRAM",
        "price": "3 134 kr"
    },
    {
        "name": "Corsair Vengeance RGB 32GB (2x16GB)",
        "specs": "DDR5 / CL36 / 32 GB / 6000 MHz / DDR5 SDRAM",
        "price": "1 439 kr"
    },
    {
        "name": "Corsair Vengeance RGB 32GB (2x16GB)",
        "specs": "DDR5 / CL30 / 32 GB / 6000 MHz / DDR5 SDRAM",
        "price": "1 790 kr"
    },
    {
        "name": "Corsair Vengeance RGB PRO 16GB (2x8GB)",
        "specs": "DDR4 / CL16 / 16 GB / 3200 MHz / DDR4 SDRAM",
        "price": "689 kr"
    },
    {
        "name": "Kingston Fury Beast 16GB (1x16GB)",
        "specs": "DDR4 / CL16 / 16 GB / 3200 MHz / DDR4 SDRAM",
        "price": "429 kr"
    },
    {
        "name": "Kingston Fury Beast RGB 32GB (2x16GB)",
        "specs": "DDR5 / CL30 / 32 GB / 6000 MHz / DDR5 SDRAM",
        "price": "1 589 kr"
    },
    {
        "name": "Corsair Vengeance 32GB (2x16GB)",
        "specs": "DDR5 / CL30 / 32 GB / 6000 MHz / DDR5 SDRAM",
        "price": "1 590 kr"
    },
    {
        "name": "Corsair Vengeance 8GB (1x8GB)",
        "specs": "SODIMM DDR4 / CL16 / 8 GB / 2400 MHz / DDR4 SDRAM",
        "price": "269 kr"
    },
    {
        "name": "Corsair Vengeance RGB PRO 16GB (2x8GB)",
        "specs": "DDR4 / CL18 / 16 GB / 3600 MHz / DDR4 SDRAM",
        "price": "689 kr"
    },
    {
        "name": "Corsair Vengeance Low Profile 8GB (2x4GB) 1600MHz",
        "specs": "DDR3 / CL9 / 8 GB / 1600 MHz / DDR3 SDRAM",
        "price": "639 kr"
    },
    {
        "name": "Kingston Fury Beast Black 64GB (2x32B)",
        "specs": "DDR5 / CL30 / 64 GB / 6000 MHz / DDR5 SDRAM",
        "price": "2 729 kr"
    },
    {
        "name": "Corsair Vengeance RGB 32GB (2x16GB)",
        "specs": "DDR5 / CL40 / 32 GB / 5200 MHz / DDR5 SDRAM",
        "price": "1 379 kr"
    },
    {
        "name": "Kingston Fury Impact 32GB (2x16GB)",
        "specs": "SODIMM DDR4 / CL20 / 32 GB / 3200 MHz / DDR4 SDRAM",
        "price": "899 kr"
    },
    {
        "name": "Kingston Fury Beast Black 32GB (2x16GB)",
        "specs": "DDR5 / CL36 / 32 GB / 5200 MHz / DDR5 SDRAM",
        "price": "1 189 kr"
    },
    {
        "name": "Kingston Fury Beast RGB 64GB (2x32GB)",
        "specs": "DDR5 / CL30 / 64 GB / 6000 MHz / DDR5 SDRAM",
        "price": "2 848 kr"
    },
    {
        "name": "Corsair Vengeance 32GB (2x16GB)",
        "specs": "DDR5 / CL40 / 32 GB / 5200 MHz / DDR5 SDRAM",
        "price": "1 199 kr"
    },
    {
        "name": "Kingston Fury Beast RGB 64GB (2x32GB)",
        "specs": "DDR5 / CL36 / 64 GB / 6000 MHz / DDR5 SDRAM",
        "price": "2 790 kr"
    },
    {
        "name": "G.SKill Trident Z Neo RGB 32GB (2x16GB)",
        "specs": "DDR4 / CL16 / 32 GB / 3600 MHz / DDR4 SDRAM",
        "price": "1 399 kr"
    },
    {
        "name": "G.Skill Trident Z5 Neo 32GB (2x16GB)",
        "specs": "DDR5 / CL30 / 32 GB / 6000 MHz / DDR5 SDRAM",
        "price": "1 569 kr"
    },
    {
        "name": "Corsair Vengeance LPX Black 16GB (2x8GB)",
        "specs": "DDR4 / CL16 / 16 GB / 3200 MHz / DDR4 SDRAM",
        "price": "519 kr"
    },
    {
        "name": "Corsair Vengeance LPX Black 16GB (2x8GB) Ryzen",
        "specs": "DDR4 / CL18 / 16 GB / 3600 MHz / DDR4 SDRAM",
        "price": "518 kr"
    },
    {
        "name": "Kingston Fury Beast Black 32GB (2x16GB)",
        "specs": "DDR5 / CL36 / 32 GB / 6000 MHz / DDR5 SDRAM",
        "price": "1 390 kr"
    },
    {
        "name": "Corsair Dominator Platinum RGB 64GB (2x32GB)",
        "specs": "DDR5 / CL40 / 64 GB / 5600 MHz / DDR5 SDRAM",
        "price": "3 149 kr"
    },
    {
        "name": "Corsair Vengeance RGB 64GB (2x32GB)",
        "specs": "DDR5 / CL32 / 64 GB / 6400 MHz / DDR5 SDRAM",
        "price": "3 189 kr"
    },
    {
        "name": "Kingston Fury Beast 64GB (2x32GB)",
        "specs": "DDR5 / CL40 / 64 GB / 5600 MHz / DDR5 SDRAM",
        "price": "2 390 kr"
    },
    {
        "name": "Kingston Fury Beast Black 16GB (2x8GB)",
        "specs": "DDR5 / CL36 / 16 GB / 6000 MHz / DDR5 SDRAM",
        "price": "849 kr"
    },
    {
        "name": "Kingston Fury Beast RGB 32GB (2x16GB)",
        "specs": "DDR5 / CL36 / 32 GB / 5200 MHz / DDR5 SDRAM",
        "price": "1 639 kr"
    },
    {
        "name": "G.Skill Trident Z5 RGB 32GB (2x16GB)",
        "specs": "DDR5 / CL32 / 32 GB / 6400 MHz / DDR5 SDRAM",
        "price": "1 587 kr"
    },
    {
        "name": "Corsair ValueSelect 8GB (1x8GB)",
        "specs": "SODIMM DDR3 / CL11 / 8 GB / 1600 MHz / DDR3L SDRAM",
        "price": "479 kr"
    },
    {
        "name": "Kingston Fury Beast Black 32GB (2x16GB)",
        "specs": "DDR5 / CL36 / 32 GB / 5600 MHz / DDR5 SDRAM",
        "price": "1 395 kr"
    },
    {
        "name": "Corsair Mac Memory 8GB (1x8GB)",
        "specs": "SODIMM DDR3 / CL11 / 8 GB / 1600 MHz / DDR3 SDRAM",
        "price": "474 kr"
    },
    {
        "name": "Kingston Fury Beast RGB 64GB (2x32GB)",
        "specs": "DDR4 / CL16 / 64 GB / 3200 MHz / DDR4 SDRAM",
        "price": "1 748 kr"
    },
    {
        "name": "Corsair Vengeance 32GB (2x16GB)",
        "specs": "DDR5 / CL40 / 32 GB / 5600 MHz / DDR5 SDRAM",
        "price": "1 299 kr"
    },
    {
        "name": "Kingston Fury Beast 16GB (2x8GB)",
        "specs": "DDR5 / CL40 / 16 GB / 5600 MHz / DDR5 SDRAM",
        "price": "719 kr"
    },
    {
        "name": "Kingston Fury Beast 64GB (2x32GB)",
        "specs": "DDR5 / CL38 / 64 GB / 5200 MHz / DDR5 SDRAM",
        "price": "2 439 kr"
    },
    {
        "name": "Kingston Fury Impact 32GB (2x16GB) / 4800Mhz / CL38",
        "specs": "SODIMM DDR5 / CL38 / 32 GB / 4800 MHz / DDR5 SDRAM",
        "price": "1 189 kr"
    },
    {
        "name": "Kingston Fury Beast 128GB (4x32GB)",
        "specs": "DDR5 / CL40 / 128 GB / 5200 MHz / DDR5 SDRAM",
        "price": "4 799 kr"
    },
    {
        "name": "Corsair Dominator Titanium Accessory Kit - Grey",
        "specs": "DDR5",
        "price": "349 kr"
    },
    {
        "name": "Corsair Vengeance 192GB (4x48GB)",
        "specs": "DDR5 / CL38 / 192 GB / 5200 MHz / DDR5 SDRAM",
        "price": "8 189 kr"
    },
    {
        "name": "Corsair ValueSelect 8GB (1x8GB)",
        "specs": "SODIMM DDR4 / CL15 / 8 GB / 2133 MHz / DDR4 SDRAM",
        "price": "269 kr"
    },
    {
        "name": "Kingston Fury Beast RGB 64GB (2x32GB)",
        "specs": "DDR5 / CL36 / 64 GB / 6000 MHz / DDR5 SDRAM",
        "price": "2 749 kr"
    },
    {
        "name": "G.SKill Trident Z5 Neo 32GB (2x16GB)",
        "specs": "DDR5 / CL32 / 32 GB / 6000 MHz / DDR5 SDRAM",
        "price": "1 539 kr"
    },
    {
        "name": "Corsair Vengeance 96GB (2x48GB)",
        "specs": "DDR5 / CL40 / 96 GB / 5600 MHz / DDR5 SDRAM",
        "price": "3 649 kr"
    },
    {
        "name": "Corsair 4GB (1x4GB)",
        "specs": "SODIMM DDR4 / CL15 / 4 GB / 2133 MHz / DDR4 SDRAM",
        "price": "189 kr"
    },
    {
        "name": "Corsair Vengeance 128GB (4x32GB)",
        "specs": "DDR5 / CL40 / 128 GB / 5600 MHz / DDR5 SDRAM",
        "price": "5 690 kr"
    },
    {
        "name": "Kingston Fury Beast Black 32GB (2x16GB)",
        "specs": "DDR5 / CL36 / 32 GB / 6000 MHz / DDR5 SDRAM",
        "price": "1 390 kr"
    },
    {
        "name": "Corsair Dominator Platinum RGB 64GB (2x32GB)",
        "specs": "DDR5 / CL40 / 64 GB / 5600 MHz / DDR5 SDRAM",
        "price": "3 149 kr"
    },
    {
        "name": "Corsair Vengeance RGB 64GB (2x32GB)",
        "specs": "DDR5 / CL32 / 64 GB / 6400 MHz / DDR5 SDRAM",
        "price": "3 189 kr"
    },
    {
        "name": "Kingston Fury Beast 64GB (2x32GB)",
        "specs": "DDR5 / CL40 / 64 GB / 5600 MHz / DDR5 SDRAM",
        "price": "2 390 kr"
    },
    {
        "name": "Kingston Fury Beast Black 16GB (2x8GB)",
        "specs": "DDR5 / CL36 / 16 GB / 6000 MHz / DDR5 SDRAM",
        "price": "849 kr"
    },
    {
        "name": "Kingston Fury Beast RGB 32GB (2x16GB)",
        "specs": "DDR5 / CL36 / 32 GB / 5200 MHz / DDR5 SDRAM",
        "price": "1 639 kr"
    },
    {
        "name": "G.Skill Trident Z5 RGB 32GB (2x16GB)",
        "specs": "DDR5 / CL32 / 32 GB / 6400 MHz / DDR5 SDRAM",
        "price": "1 587 kr"
    },
    {
        "name": "Corsair ValueSelect 8GB (1x8GB)",
        "specs": "SODIMM DDR3 / CL11 / 8 GB / 1600 MHz / DDR3L SDRAM",
        "price": "479 kr"
    },
    {
        "name": "Kingston Fury Beast Black 32GB (2x16GB)",
        "specs": "DDR5 / CL36 / 32 GB / 5600 MHz / DDR5 SDRAM",
        "price": "1 395 kr"
    },
    {
        "name": "Corsair Mac Memory 8GB (1x8GB)",
        "specs": "SODIMM DDR3 / CL11 / 8 GB / 1600 MHz / DDR3 SDRAM",
        "price": "474 kr"
    },
    {
        "name": "Kingston Fury Beast RGB 64GB (2x32GB)",
        "specs": "DDR4 / CL16 / 64 GB / 3200 MHz / DDR4 SDRAM",
        "price": "1 748 kr"
    },
    {
        "name": "Corsair Vengeance 32GB (2x16GB)",
        "specs": "DDR5 / CL40 / 32 GB / 5600 MHz / DDR5 SDRAM",
        "price": "1 299 kr"
    },
    {
        "name": "Kingston Fury Beast 16GB (2x8GB)",
        "specs": "DDR5 / CL40 / 16 GB / 5600 MHz / DDR5 SDRAM",
        "price": "719 kr"
    },
    {
        "name": "Kingston Fury Beast 64GB (2x32GB)",
        "specs": "DDR5 / CL38 / 64 GB / 5200 MHz / DDR5 SDRAM",
        "price": "2 439 kr"
    },
    {
        "name": "Kingston Fury Impact 32GB (2x16GB) / 4800Mhz / CL38",
        "specs": "SODIMM DDR5 / CL38 / 32 GB / 4800 MHz / DDR5 SDRAM",
        "price": "1 189 kr"
    },
    {
        "name": "Kingston Fury Beast 128GB (4x32GB)",
        "specs": "DDR5 / CL40 / 128 GB / 5200 MHz / DDR5 SDRAM",
        "price": "4 799 kr"
    },
    {
        "name": "Corsair Dominator Titanium Accessory Kit - Grey",
        "specs": "DDR5",
        "price": "349 kr"
    },
    {
        "name": "Corsair Vengeance 192GB (4x48GB)",
        "specs": "DDR5 / CL38 / 192 GB / 5200 MHz / DDR5 SDRAM",
        "price": "8 189 kr"
    },
    {
        "name": "Corsair ValueSelect 8GB (1x8GB)",
        "specs": "SODIMM DDR4 / CL15 / 8 GB / 2133 MHz / DDR4 SDRAM",
        "price": "269 kr"
    },
    {
        "name": "Kingston Fury Beast RGB 64GB (2x32GB)",
        "specs": "DDR5 / CL36 / 64 GB / 6000 MHz / DDR5 SDRAM",
        "price": "2 749 kr"
    },
    {
        "name": "G.SKill Trident Z5 Neo 32GB (2x16GB)",
        "specs": "DDR5 / CL32 / 32 GB / 6000 MHz / DDR5 SDRAM",
        "price": "1 539 kr"
    },
    {
        "name": "Corsair Vengeance 96GB (2x48GB)",
        "specs": "DDR5 / CL40 / 96 GB / 5600 MHz / DDR5 SDRAM",
        "price": "3 649 kr"
    },
    {
        "name": "Corsair 4GB (1x4GB)",
        "specs": "SODIMM DDR4 / CL15 / 4 GB / 2133 MHz / DDR4 SDRAM",
        "price": "189 kr"
    },
    {
        "name": "Corsair Vengeance 128GB (4x32GB)",
        "specs": "DDR5 / CL40 / 128 GB / 5600 MHz / DDR5 SDRAM",
        "price": "5 690 kr"
    },
    {
        "name": "Corsair Vengeance 64GB (2x32GB)",
        "specs": "DDR5 / CL40 / 64 GB / 5600 MHz / DDR5 SDRAM",
        "price": "2 397 kr"
    },
    {
        "name": "Kingston Fury Beast RGB 64GB (2x32GB)",
        "specs": "DDR5 / CL40 / 64 GB / 6000 MHz / DDR5 SDRAM",
        "price": "2 745 kr"
    },
    {
        "name": "Samsung PC4-25600U 32GB (1x32GB)",
        "specs": "DDR4 / CL22 / 32 GB / 3200 MHz / DDR4 SDRAM",
        "price": "1 419 kr"
    },
    {
        "name": "Corsair Vengeance RGB 32GB (2x16GB)",
        "specs": "DDR5 / CL40 / 32 GB / 5600 MHz / DDR5 SDRAM",
        "price": "1 439 kr"
    },
    {
        "name": "Kingston Fury Renegade 16GB (1x16GB)",
        "specs": "DDR5 / CL38 / 16 GB / 7200 MHz / DDR5 SDRAM",
        "price": "1 199 kr"
    },
    {
        "name": "G.Skill Flare X5 32GB (2x16GB)",
        "specs": "DDR5 / CL36 / 32 GB / 6000 MHz / DDR5 SDRAM",
        "price": "1 499 kr"
    },
    {
        "name": "Corsair Vengeance 48GB (2x24GB)",
        "specs": "DDR5 / CL38 / 48 GB / 5200 MHz / DDR5 SDRAM",
        "price": "1 849 kr"
    },
    {
        "name": "Kingston Fury Beast RGB 64GB (2x32GB)",
        "specs": "DDR5 / CL36 / 64 GB / 5600 MHz / DDR5 SDRAM",
        "price": "2 559 kr"
    },
    {
        "name": "Corsair ValueSelect 16GB (2x8GB) 1600MHZ",
        "specs": "SODIMM DDR3 / CL11 / 16 GB / 1600 MHz / DDR3L SDRAM",
        "price": "999 kr"
    },
    {
        "name": "G.Skill Trident TZ5 32GB (2x16GB)",
        "specs": "DDR5 / CL32 / 32 GB / 6400 MHz / DDR5 SDRAM",
        "price": "1 679 kr"
    },
    {
        "name": "Corsair Vengeance LPX Black 8GB (2x4GB)",
        "specs": "DDR4 / CL16 / 8 GB / 2666 MHz / DDR4 SDRAM",
        "price": "399 kr"
    },
    {
        "name": "Corsair Dominator Platinum RGB 32GB (4x8GB)",
        "specs": "DDR4 / CL16 / 32 GB / 3200 MHz / DDR4 SDRAM",
        "price": "1 923 kr"
    },
    {
        "name": "Corsair Vengeance 48GB (2x24GB)",
        "specs": "DDR5 / CL38 / 48 GB / 5200 MHz / DDR5 SDRAM",
        "price": "1 990 kr"
    },
    {
        "name": "Corsair Vengeance 48GB (2x24GB)",
        "specs": "DDR5 / CL40 / 48 GB / 5600 MHz / DDR5 SDRAM",
        "price": "1 999 kr"
    },
    {
        "name": "Corsair Dominator Titanium Accessory Kit - White",
        "specs": "DDR5",
        "price": "349 kr"
    },
    {
        "name": "Corsair Vengeance RGB 32GB (2x16GB)",
        "specs": "DDR5 / CL36 / 32 GB / 6000 MHz / DDR5 SDRAM",
        "price": "1 690 kr"
    },
    {
        "name": "Corsair Vengeance RGB 32GB (2x16GB)",
        "specs": "DDR5 / CL36 / 32 GB / 6000 MHz / DDR5 SDRAM",
        "price": "1 790 kr"
    },
    {
        "name": "G.SKill Trident Z5 Neo RGB 64GB (2x32GB)",
        "specs": "DDR5 / CL30 / 64 GB / 6000 MHz / DDR5 SDRAM",
        "price": "2 849 kr"
    },
    {
        "name": "Corsair Vengeance LPX Black 32GB (2x16GB)",
        "specs": "DDR4 / CL16 / 32 GB / 2666 MHz / DDR4 SDRAM",
        "price": "818 kr"
    },
    {
        "name": "Corsair Vengeance RGB RS 16GB (2x8GB)",
        "specs": "DDR4 / CL16 / 16 GB / 3200 MHz / DDR4 SDRAM",
        "price": "549 kr\n639 kr"
    },
    {
        "name": "Kingston Fury Beast 64GB (2x32GB)",
        "specs": "DDR5 / CL36 / 64 GB / 6000 MHz / DDR5 SDRAM",
        "price": "2 699 kr"
    },
    {
        "name": "Corsair Vengeance 32GB (2x16GB)",
        "specs": "SODIMM DDR4 / CL18 / 32 GB / 2666 MHz / DDR4 SDRAM",
        "price": "818 kr"
    },
    {
        "name": "Corsair Vengeance LPX Black 16GB (2x8GB)",
        "specs": "DDR4 / CL18 / 16 GB / 3600 MHz / DDR4 SDRAM",
        "price": "509 kr"
    },
    {
        "name": "Kingston FURY Beast RGB 32GB (2x16GB) / 6000 Mhz / DDR5 / CL36 / KF560C36BBE2AK2-32 - Expo",
        "specs": "DDR5 / CL36 / 32 GB / 6000 MHz / DDR5 SDRAM",
        "price": "1 890 kr"
    },
    {
        "name": "Kingston Fury Beast Black 16GB (2x8GB)",
        "specs": "DDR5 / CL30 / 16 GB / 6000 MHz / DDR5 SDRAM",
        "price": "839 kr"
    },
    {
        "name": "Kingston Fury Beast RGB 16GB (2x8GB)",
        "specs": "DDR4 / CL16 / 16 GB / 3200 MHz / DDR4 SDRAM",
        "price": "659 kr"
    },
    {
        "name": "Kingston Fury Beast RGB 32GB (2x16GB)",
        "specs": "DDR4 / CL16 / 32 GB / 3200 MHz / DDR4 SDRAM",
        "price": "990 kr"
    },
    {
        "name": "Corsair Vengeance 16GB (2x8GB)",
        "specs": "DDR3 / CL10 / 16 GB / 1600 MHz / DDR3 SDRAM",
        "price": "1 049 kr"
    },
    {
        "name": "Kingston Fury Beast RGB 32GB (2x16GB)",
        "specs": "DDR5 / CL36 / 32 GB / 5600 MHz / DDR5 SDRAM",
        "price": "1 449 kr"
    },
    {
        "name": "Corsair Vengeance LPX Black 64GB (2x32GB)",
        "specs": "DDR4 / CL16 / 64 GB / 3200 MHz / DDR4 SDRAM",
        "price": "1 569 kr"
    },
    {
        "name": "Corsair Mac Memory 8GB (2x4GB)",
        "specs": "SODIMM DDR3 / CL9 / 8 GB / 1333 MHz / DDR3 SDRAM",
        "price": "539 kr"
    },
    {
        "name": "Corsair Vengeance 32GB (2x16GB)",
        "specs": "DDR5 / CL30 / 32 GB / 6000 MHz / DDR5 SDRAM",
        "price": "1 490 kr"
    },
    {
        "name": "Corsair Vengeance RGB PRO 32GB (2x16GB) Ryzen",
        "specs": "DDR4 / CL18 / 32 GB / 3600 MHz / DDR4 SDRAM",
        "price": "999 kr"
    },
    {
        "name": "Kingston Fury Beast RGB 32GB (2x16GB)",
        "specs": "DDR5 / CL30 / 32 GB / 6000 MHz / DDR5 SDRAM",
        "price": "1 590 kr"
    },
    {
        "name": "Corsair Vengeance LPX Black 16GB (2x8GB)",
        "specs": "DDR4 / CL16 / 16 GB / 2666 MHz / DDR4 SDRAM",
        "price": "519 kr"
    },
    {
        "name": "Corsair Vengeance 32GB (2x16GB)",
        "specs": "DDR5 / CL36 / 32 GB / 6000 MHz / DDR5 SDRAM",
        "price": "1 290 kr"
    },
    {
        "name": "Corsair Vengeance LPX Black 32GB (2x16GB)",
        "specs": "DDR4 / CL16 / 32 GB / 3200 MHz / DDR4 SDRAM",
        "price": "819 kr"
    },
    {
        "name": "Corsair Dominator Titanium Accessory Kit - Black",
        "specs": "DDR5",
        "price": "349 kr"
    },
    {
        "name": "Kingston Fury Impact 16GB (1x16GB) / 4800Mhz / CL38",
        "specs": "SODIMM DDR5 / CL38 / 16 GB / 4800 MHz / DDR5 SDRAM",
        "price": "639 kr"
    },
    {
        "name": "Corsair Vengeance RGB 32GB (2x16GB)",
        "specs": "DDR5 / CL36 / 32 GB / 6000 MHz / DDR5 SDRAM",
        "price": "1 490 kr"
    },
    {
        "name": "Kingston Fury Beast 32GB (2x16GB)",
        "specs": "DDR4 / CL16 / 32 GB / 3200 MHz / DDR4 SDRAM",
        "price": "829 kr"
    },
    {
        "name": "Corsair Vengeance LPX Black 16GB (2x8GB)",
        "specs": "DDR4 / CL16 / 16 GB / 3200 MHz / DDR4 SDRAM",
        "price": "499 kr"
    },
    {
        "name": "Kingston Fury Beast Black 32GB (2x16GB)",
        "specs": "DDR5 / CL30 / 32 GB / 6000 MHz / DDR5 SDRAM",
        "price": "1 469 kr"
    },
    {
        "name": "Kingston Fury Impact 16GB (1x16GB)",
        "specs": "SODIMM DDR4 / CL20 / 16 GB / 3200 MHz / DDR4 SDRAM",
        "price": "419 kr"
    },
    {
        "name": "Corsair Vengeance RGB 32GB (2x16GB)",
        "specs": "DDR5 / CL36 / 32 GB / 6200 MHz / DDR5 SDRAM",
        "price": "1 739 kr"
    },
    {
        "name": "Kingston Fury Beast RGB 32GB (2x16GB)",
        "specs": "DDR5 / CL30 / 32 GB / 6000 MHz / DDR5 SDRAM",
        "price": "1 590 kr"
    },
    {
        "name": "Corsair Vengeance 16GB (2x8GB)",
        "specs": "SODIMM DDR4 / CL18 / 16 GB / 2666 MHz / DDR4 SDRAM",
        "price": "519 kr"
    },
    {
        "name": "Kingston Fury Impact 8GB (1x8GB)",
        "specs": "SODIMM DDR4 / CL20 / 8 GB / 3200 MHz / DDR4 SDRAM",
        "price": "255 kr"
    },
    {
        "name": "Corsair Vengeance LPX Black 8GB (1x8GB)",
        "specs": "DDR4 / CL16 / 8 GB / 2666 MHz / DDR4 SDRAM",
        "price": "259 kr"
    },
    {
        "name": "Kingston Fury Beast Black 32GB (2x16GB)",
        "specs": "DDR5 / CL30 / 32 GB / 6000 MHz / DDR5 SDRAM",
        "price": "1 589 kr"
    },
    {
        "name": "Corsair Vengeance 32GB (2x16GB)",
        "specs": "DDR5 / CL36 / 32 GB / 6000 MHz / DDR5 SDRAM",
        "price": "1 389 kr"
    },
    {
        "name": "Corsair Vengeance 64GB (2x32GB)",
        "specs": "DDR5 / CL32 / 64 GB / 6600 MHz / DDR5 SDRAM",
        "price": "3 134 kr"
    },
    {
        "name": "Corsair Vengeance RGB 32GB (2x16GB)",
        "specs": "DDR5 / CL36 / 32 GB / 6000 MHz / DDR5 SDRAM",
        "price": "1 439 kr"
    },
    {
        "name": "Corsair Vengeance RGB 32GB (2x16GB)",
        "specs": "DDR5 / CL30 / 32 GB / 6000 MHz / DDR5 SDRAM",
        "price": "1 790 kr"
    },
    {
        "name": "Corsair Vengeance RGB PRO 16GB (2x8GB)",
        "specs": "DDR4 / CL16 / 16 GB / 3200 MHz / DDR4 SDRAM",
        "price": "689 kr"
    },
    {
        "name": "Kingston Fury Beast 16GB (1x16GB)",
        "specs": "DDR4 / CL16 / 16 GB / 3200 MHz / DDR4 SDRAM",
        "price": "429 kr"
    },
    {
        "name": "Kingston Fury Beast RGB 32GB (2x16GB)",
        "specs": "DDR5 / CL30 / 32 GB / 6000 MHz / DDR5 SDRAM",
        "price": "1 589 kr"
    },
    {
        "name": "Corsair Vengeance 32GB (2x16GB)",
        "specs": "DDR5 / CL30 / 32 GB / 6000 MHz / DDR5 SDRAM",
        "price": "1 590 kr"
    },
    {
        "name": "Corsair Vengeance 8GB (1x8GB)",
        "specs": "SODIMM DDR4 / CL16 / 8 GB / 2400 MHz / DDR4 SDRAM",
        "price": "269 kr"
    },
    {
        "name": "Corsair Vengeance RGB PRO 16GB (2x8GB)",
        "specs": "DDR4 / CL18 / 16 GB / 3600 MHz / DDR4 SDRAM",
        "price": "689 kr"
    },
    {
        "name": "Corsair Vengeance Low Profile 8GB (2x4GB) 1600MHz",
        "specs": "DDR3 / CL9 / 8 GB / 1600 MHz / DDR3 SDRAM",
        "price": "639 kr"
    },
    {
        "name": "Kingston Fury Beast Black 64GB (2x32B)",
        "specs": "DDR5 / CL30 / 64 GB / 6000 MHz / DDR5 SDRAM",
        "price": "2 729 kr"
    },
    {
        "name": "Corsair Vengeance RGB 32GB (2x16GB)",
        "specs": "DDR5 / CL40 / 32 GB / 5200 MHz / DDR5 SDRAM",
        "price": "1 379 kr"
    },
    {
        "name": "Kingston Fury Impact 32GB (2x16GB)",
        "specs": "SODIMM DDR4 / CL20 / 32 GB / 3200 MHz / DDR4 SDRAM",
        "price": "899 kr"
    },
    {
        "name": "Kingston Fury Beast Black 32GB (2x16GB)",
        "specs": "DDR5 / CL36 / 32 GB / 5200 MHz / DDR5 SDRAM",
        "price": "1 189 kr"
    },
    {
        "name": "Kingston Fury Beast RGB 64GB (2x32GB)",
        "specs": "DDR5 / CL30 / 64 GB / 6000 MHz / DDR5 SDRAM",
        "price": "2 848 kr"
    },
    {
        "name": "Corsair Vengeance 32GB (2x16GB)",
        "specs": "DDR5 / CL40 / 32 GB / 5200 MHz / DDR5 SDRAM",
        "price": "1 199 kr"
    },
    {
        "name": "Kingston Fury Beast RGB 64GB (2x32GB)",
        "specs": "DDR5 / CL36 / 64 GB / 6000 MHz / DDR5 SDRAM",
        "price": "2 790 kr"
    },
    {
        "name": "G.SKill Trident Z Neo RGB 32GB (2x16GB)",
        "specs": "DDR4 / CL16 / 32 GB / 3600 MHz / DDR4 SDRAM",
        "price": "1 399 kr"
    },
    {
        "name": "G.Skill Trident Z5 Neo 32GB (2x16GB)",
        "specs": "DDR5 / CL30 / 32 GB / 6000 MHz / DDR5 SDRAM",
        "price": "1 569 kr"
    },
    {
        "name": "Corsair Vengeance LPX Black 16GB (2x8GB)",
        "specs": "DDR4 / CL16 / 16 GB / 3200 MHz / DDR4 SDRAM",
        "price": "519 kr"
    },
    {
        "name": "Corsair Vengeance LPX Black 16GB (2x8GB) Ryzen",
        "specs": "DDR4 / CL18 / 16 GB / 3600 MHz / DDR4 SDRAM",
        "price": "518 kr"
    },
    {
        "name": "Corsair Vengeance 32GB (2x16GB)",
        "specs": "SODIMM DDR4 / CL16 / 32 GB / 2400 MHz / DDR4 SDRAM",
        "price": "799 kr"
    },
    {
        "name": "Corsair Vengeance 64GB (2x32GB)",
        "specs": "DDR5 / CL40 / 64 GB / 5600 MHz / DDR5 SDRAM",
        "price": "2 299 kr"
    },
    {
        "name": "Corsair Vengeance LPX Black 16GB (2x8GB)",
        "specs": "DDR4 / CL14 / 16 GB / 2400 MHz / DDR4 SDRAM",
        "price": "489 kr"
    },
    {
        "name": "G.Skill Ripjaws S5 32GB (2x16GB)",
        "specs": "DDR5 / CL34 / 32 GB / 6800 MHz / DDR5 SDRAM",
        "price": "1 619 kr"
    },
    {
        "name": "Kingston Fury Impact 32GB (1x32GB) / 4800Mhz / CL38",
        "specs": "SODIMM DDR5 / CL38 / 32 GB / 4800 MHz / DDR5 SDRAM",
        "price": "1 159 kr"
    },
    {
        "name": "Kingston Fury Beast RGB 64GB (2x32GB) / 6000MHz / DDR5 / CL30 / KF560C30BBAK2-64 (Fyndvara - Klass 1)",
        "specs": "DDR5",
        "price": "2 705 kr\n2 848 kr"
    },
    {
        "name": "G.SKill Trident Z5 Neo RGB 32GB (2x16GB)",
        "specs": "DDR5 / CL32 / 32 GB / 3000 MHz / DDR5 SDRAM",
        "price": "1 549 kr"
    },
    {
        "name": "G.SKill Trident Z5 Neo RGB 32GB (2x16GB) / 6000MHz / DDR5 / CL32 / F5-6000J3238F16GX2-TZ5NR (Fyndvara - Klass 1)",
        "specs": "DDR5",
        "price": "1 475 kr"
    },
    {
        "name": "Corsair Vengeance 32GB (2x16GB)",
        "specs": "SODIMM DDR4 / CL16 / 32 GB / 2400 MHz / DDR4 SDRAM",
        "price": "799 kr"
    },
    {
        "name": "Corsair Vengeance 64GB (2x32GB)",
        "specs": "DDR5 / CL40 / 64 GB / 5600 MHz / DDR5 SDRAM",
        "price": "2 299 kr"
    },
    {
        "name": "Corsair Vengeance LPX Black 16GB (2x8GB)",
        "specs": "DDR4 / CL14 / 16 GB / 2400 MHz / DDR4 SDRAM",
        "price": "489 kr"
    },
    {
        "name": "G.Skill Ripjaws S5 32GB (2x16GB)",
        "specs": "DDR5 / CL34 / 32 GB / 6800 MHz / DDR5 SDRAM",
        "price": "1 619 kr"
    },
    {
        "name": "Kingston Fury Impact 32GB (1x32GB) / 4800Mhz / CL38",
        "specs": "SODIMM DDR5 / CL38 / 32 GB / 4800 MHz / DDR5 SDRAM",
        "price": "1 159 kr"
    },
    {
        "name": "Kingston Fury Beast RGB 64GB (2x32GB) / 6000MHz / DDR5 / CL30 / KF560C30BBAK2-64 (Fyndvara - Klass 1)",
        "specs": "DDR5",
        "price": "2 705 kr\n2 848 kr"
    },
    {
        "name": "G.SKill Trident Z5 Neo RGB 32GB (2x16GB)",
        "specs": "DDR5 / CL32 / 32 GB / 3000 MHz / DDR5 SDRAM",
        "price": "1 549 kr"
    },
    {
        "name": "G.SKill Trident Z5 Neo RGB 32GB (2x16GB) / 6000MHz / DDR5 / CL32 / F5-6000J3238F16GX2-TZ5NR (Fyndvara - Klass 1)",
        "specs": "DDR5",
        "price": "1 475 kr"
    },
    {
        "name": "Corsair Vengeance 32GB (2x16GB)",
        "specs": "SODIMM DDR4 / CL16 / 32 GB / 2400 MHz / DDR4 SDRAM",
        "price": "799 kr"
    },
    {
        "name": "Corsair Vengeance 64GB (2x32GB)",
        "specs": "DDR5 / CL40 / 64 GB / 5600 MHz / DDR5 SDRAM",
        "price": "2 299 kr"
    },
    {
        "name": "Corsair Vengeance LPX Black 16GB (2x8GB)",
        "specs": "DDR4 / CL14 / 16 GB / 2400 MHz / DDR4 SDRAM",
        "price": "489 kr"
    },
    {
        "name": "G.Skill Ripjaws S5 32GB (2x16GB)",
        "specs": "DDR5 / CL34 / 32 GB / 6800 MHz / DDR5 SDRAM",
        "price": "1 619 kr"
    },
    {
        "name": "Kingston Fury Impact 32GB (1x32GB) / 4800Mhz / CL38",
        "specs": "SODIMM DDR5 / CL38 / 32 GB / 4800 MHz / DDR5 SDRAM",
        "price": "1 159 kr"
    },
    {
        "name": "Kingston Fury Beast RGB 64GB (2x32GB) / 6000MHz / DDR5 / CL30 / KF560C30BBAK2-64 (Fyndvara - Klass 1)",
        "specs": "DDR5",
        "price": "2 705 kr\n2 848 kr"
    },
    {
        "name": "G.SKill Trident Z5 Neo RGB 32GB (2x16GB)",
        "specs": "DDR5 / CL32 / 32 GB / 3000 MHz / DDR5 SDRAM",
        "price": "1 549 kr"
    },
    {
        "name": "G.SKill Trident Z5 Neo RGB 32GB (2x16GB) / 6000MHz / DDR5 / CL32 / F5-6000J3238F16GX2-TZ5NR (Fyndvara - Klass 1)",
        "specs": "DDR5",
        "price": "1 475 kr"
    }
]