[
    {
        "name":"Kingston Fury Renegade 500GB",
        "brand":"Kingston",
        "form_factor":"M.2 2280",
        "capacity":"500 GB",
        "interface":"PCI Express 4.0 (NVMe)",
        "read_speed":7300.0,
        "write_speed":null,
        "price":749
    },
    {
        "name":"WD Black SSD SN770 2TB",
        "brand":"WD",
        "form_factor":"M.2 2280",
        "capacity":"2 TB",
        "interface":"PCI Express 4.0 x4 (NVMe)",
        "read_speed":5150.0,
        "write_speed":null,
        "price":1789
    },
    {
        "name":"Kingston NV3 M.2 2TB",
        "brand":"Kingston",
        "form_factor":"M.2 2280",
        "capacity":"2 TB",
        "interface":"PCI Express 4.0 x4 (NVMe)",
        "read_speed":6000.0,
        "write_speed":null,
        "price":1590
    },
    {
        "name":"Kingston NV3 M.2 500GB",
        "brand":"Kingston",
        "form_factor":"M.2 2280",
        "capacity":"500 GB",
        "interface":"PCI Express 4.0 x4 (NVMe)",
        "read_speed":5000.0,
        "write_speed":null,
        "price":599
    },
    {
        "name":"Kingston Fury Renegade Heatsink 1TB",
        "brand":"Kingston",
        "form_factor":"M.2 2280",
        "capacity":"1 TB",
        "interface":"PCI Express 4.0 x4 (NVMe)",
        "read_speed":7300.0,
        "write_speed":null,
        "price":1289
    },
    {
        "name":"Samsung 990 EVO Plus 1TB",
        "brand":"Samsung",
        "form_factor":"M.2 2280",
        "capacity":"1 TB",
        "interface":"PCI Express 5.0 x2 (NVMe), PCI Express 4.0 x4 (NVMe)",
        "read_speed":7150.0,
        "write_speed":null,
        "price":1290
    },
    {
        "name":"Kingston KC3000 M.2 4TB",
        "brand":"Kingston",
        "form_factor":"M.2 2280",
        "capacity":"4096 GB",
        "interface":"PCI Express 4.0 (NVMe)",
        "read_speed":7000.0,
        "write_speed":null,
        "price":3490
    },
    {
        "name":"WD SSD Blue SN580 2TB",
        "brand":"WD",
        "form_factor":"M.2 2280",
        "capacity":"2 TB",
        "interface":"PCI Express 4.0 x4 (NVMe)",
        "read_speed":4150.0,
        "write_speed":null,
        "price":1599
    },
    {
        "name":"Kingston Fury Renegade Heatsink 2TB",
        "brand":"Kingston",
        "form_factor":"M.2 2280",
        "capacity":"2 TB",
        "interface":"PCI Express 4.0 x4 (NVMe)",
        "read_speed":7300.0,
        "write_speed":null,
        "price":2189
    },
    {
        "name":"Samsung 990 Pro with Heatsink 1TB",
        "brand":"Samsung",
        "form_factor":"M.2 2280",
        "capacity":"1 TB",
        "interface":"PCI Express 4.0 x4 (NVMe)",
        "read_speed":7450.0,
        "write_speed":null,
        "price":1590
    },
    {
        "name":"WD SSD Blue SN580 1TB",
        "brand":"WD",
        "form_factor":"M.2 2280",
        "capacity":"1 TB",
        "interface":"PCI Express 4.0 x4 (NVMe)",
        "read_speed":4150.0,
        "write_speed":null,
        "price":979
    },
    {
        "name":"Corsair MP600 PRO NH 1TB",
        "brand":"Corsair",
        "form_factor":"M.2 2280",
        "capacity":"1 TB",
        "interface":"PCI Express 4.0 x4 (NVMe)",
        "read_speed":7000.0,
        "write_speed":null,
        "price":1399
    },
    {
        "name":"Corsair MP600 CORE XT 2TB",
        "brand":"Corsair",
        "form_factor":"M.2 2280",
        "capacity":"2 TB",
        "interface":"PCI Express 4.0 x4 (NVMe)",
        "read_speed":null,
        "write_speed":null,
        "price":2299
    },
    {
        "name":"Seagate FireCuda 510 SSD 1TB M.2 NVMe",
        "brand":"Seagate",
        "form_factor":"M.2 2280",
        "capacity":"1 TB",
        "interface":"PCI Express 3.0 x4 (NVMe)",
        "read_speed":3450.0,
        "write_speed":null,
        "price":2149
    },
    {
        "name":"Corsair MP600 PRO NH 8TB",
        "brand":"Corsair",
        "form_factor":"M.2 2280",
        "capacity":"8 TB",
        "interface":"PCI Express 4.0 x4 (NVMe)",
        "read_speed":7000.0,
        "write_speed":null,
        "price":12569
    },
    {
        "name":"Kingston Fury Renegade M.2 2TB + be quiet! MC1 heatsink",
        "brand":"Kingston",
        "form_factor":"M.2 2280",
        "capacity":"2 TB",
        "interface":"PCI Express 4.0 x4 (NVMe)",
        "read_speed":null,
        "write_speed":null,
        "price":1829
    },
    {
        "name":"Corsair MP700 Pro - 2TB",
        "brand":"Corsair",
        "form_factor":"M.2 2280",
        "capacity":"2 TB",
        "interface":"PCI Express 5.0 x4 (NVMe)",
        "read_speed":12400.0,
        "write_speed":null,
        "price":4190
    },
    {
        "name":"Samsung 990 Pro with Heatsink 4TB",
        "brand":"Samsung",
        "form_factor":"M.2 2280",
        "capacity":"4 TB",
        "interface":"PCI Express 4.0 x4 (NVMe)",
        "read_speed":7450.0,
        "write_speed":null,
        "price":3889
    },
    {
        "name":"Corsair MP700 Pro - 1TB",
        "brand":"Corsair",
        "form_factor":"M.2 2280",
        "capacity":"1 TB",
        "interface":"PCI Express 5.0 x4 (NVMe)",
        "read_speed":11700.0,
        "write_speed":null,
        "price":2599
    },
    {
        "name":"Kingston NV2 M.2 500GB",
        "brand":"Kingston",
        "form_factor":"M.2 2280",
        "capacity":"500 GB",
        "interface":"PCI Express 4.0 x4 (NVMe)",
        "read_speed":3500.0,
        "write_speed":null,
        "price":549
    },
    {
        "name":"Samsung 990 Pro 4TB",
        "brand":"Samsung",
        "form_factor":"M.2 2280",
        "capacity":"4 TB",
        "interface":"PCI Express 4.0 x4 (NVMe)",
        "read_speed":7450.0,
        "write_speed":null,
        "price":3990
    }
]